CODEOWNERS
LICENSE
MANIFEST.in
README.md
RELEASE.md
setup.py
requirements/run.txt
requirements/test.txt
starz/__init__.py
starz/__main__.py
starz.egg-info/PKG-INFO
starz.egg-info/SOURCES.txt
starz.egg-info/dependency_links.txt
starz.egg-info/entry_points.txt
starz.egg-info/requires.txt
starz.egg-info/top_level.txt