Metadata-Version: 2.1
Name: starz
Version: 0.2.2
Summary: Sized Tape ARchiveZ
Home-page: https://github.com/Semi-ATE/starz
Author: Tom Hören
Maintainer: Semi-ATE
Maintainer-email: info@Semi-ATE.com
License: MIT
Keywords: tar,archives,docker,vivado,petalinux
Platform: Windows
Platform: Linux
Platform: MacOS
Classifier: License :: OSI Approved :: MIT License
Classifier: Operating System :: POSIX :: Linux
Classifier: Operating System :: MacOS :: MacOS X
Classifier: Operating System :: Microsoft :: Windows :: Windows 10
Classifier: Natural Language :: English
Classifier: Programming Language :: Python
Classifier: Programming Language :: Python :: 3 :: Only
Classifier: Programming Language :: Python :: 3.7
Classifier: Programming Language :: Python :: 3.8
Classifier: Programming Language :: Python :: 3.9
Classifier: Development Status :: 4 - Beta
Classifier: Intended Audience :: Science/Research
Classifier: Intended Audience :: Developers
Classifier: Topic :: Software Development :: Libraries
Classifier: Topic :: Software Development :: Libraries :: Python Modules
Classifier: Topic :: Scientific/Engineering
Requires-Python: >=3.7
